nornir_easy_netmiko/.git/config
nornir_easy_netmiko/.git/description
nornir_easy_netmiko/.git/HEAD
nornir_easy_netmiko/.git/hooks/applypatch-msg.sample
nornir_easy_netmiko/.git/hooks/commit-msg.sample
nornir_easy_netmiko/.git/hooks/fsmonitor-watchman.sample
nornir_easy_netmiko/.git/hooks/post-update.sample
nornir_easy_netmiko/.git/hooks/pre-applypatch.sample
nornir_easy_netmiko/.git/hooks/pre-commit.sample
nornir_easy_netmiko/.git/hooks/pre-merge-commit.sample
nornir_easy_netmiko/.git/hooks/pre-push.sample
nornir_easy_netmiko/.git/hooks/pre-rebase.sample
nornir_easy_netmiko/.git/hooks/pre-receive.sample
nornir_easy_netmiko/.git/hooks/prepare-commit-msg.sample
nornir_easy_netmiko/.git/hooks/push-to-checkout.sample
nornir_easy_netmiko/.git/hooks/update.sample
nornir_easy_netmiko/.git/index
nornir_easy_netmiko/.git/info/exclude
nornir_easy_netmiko/.git/logs/HEAD
nornir_easy_netmiko/.git/logs/refs/heads/main
nornir_easy_netmiko/.git/logs/refs/remotes/origin/HEAD
nornir_easy_netmiko/.git/objects/pack/pack-be3d3a825c297fe6a3cc1d036097fe20be9cf0f7.idx
nornir_easy_netmiko/.git/objects/pack/pack-be3d3a825c297fe6a3cc1d036097fe20be9cf0f7.pack
nornir_easy_netmiko/.git/packed-refs
nornir_easy_netmiko/.git/refs/heads/main
nornir_easy_netmiko/.git/refs/remotes/origin/HEAD
nornir_easy_netmiko/config/groups.yaml
nornir_easy_netmiko/config/hosts.yaml
nornir_easy_netmiko/config/settings.py
nornir_easy_netmiko/main.py
nornir_easy_netmiko/manage.py
nornir_easy_netmiko/nornir.log
nornir_easy_netmiko/nornir_easy_netmiko/__init__.py
nornir_easy_netmiko/nornir_easy_netmiko/connections/__init__.py
nornir_easy_netmiko/nornir_easy_netmiko/connections/netmiko.py
nornir_easy_netmiko/nornir_easy_netmiko/errors/__init__.py
nornir_easy_netmiko/nornir_easy_netmiko/tasks/__init__.py
nornir_easy_netmiko/nornir_easy_netmiko/tasks/netmiko_commit.py
nornir_easy_netmiko/nornir_easy_netmiko/tasks/netmiko_file_transfer.py
nornir_easy_netmiko/nornir_easy_netmiko/tasks/netmiko_multiline.py
nornir_easy_netmiko-1.1.7.dist-info/entry_points.txt
nornir_easy_netmiko-1.1.7.dist-info/METADATA
nornir_easy_netmiko-1.1.7.dist-info/WHEEL
nornir_easy_netmiko-1.1.7.dist-info/RECORD
