Metadata-Version: 2.1
Name: nornir-easy-netmiko
Version: 1.1.7
Summary: Netmiko's plugins for Nornir. Support jinja2 and optimized exception.
Home-page: https://github.com/Des1r3/nornir_easy_netmiko
License: Apache-2.0
Author: Des1r3
Author-email: linzx@anonymous.com
Requires-Python: >=3.7,<4.0
Classifier: License :: OSI Approved :: Apache Software License
Classifier: Programming Language :: Python :: 3
Classifier: Programming Language :: Python :: 3.7
Classifier: Programming Language :: Python :: 3.8
Classifier: Programming Language :: Python :: 3.9
Classifier: Programming Language :: Python :: 3.10
Classifier: Programming Language :: Python :: 3.11
Requires-Dist: jinja2 (>=3.0,<4.0)
Requires-Dist: netmiko (>=4.0.0,<5.0.0)
Project-URL: Repository, https://github.com/Des1r3/nornir_easy_netmiko
